fake_headers/__init__.py
fake_headers/browsers.py
fake_headers/headers.py
fake_headers/platforms.py
fake_headers-1.0.2.dist-info/LICENSE
fake_headers-1.0.2.dist-info/METADATA
fake_headers-1.0.2.dist-info/WHEEL
fake_headers-1.0.2.dist-info/top_level.txt
fake_headers-1.0.2.dist-info/RECORD
