Metadata-Version: 2.1
Name: fake-headers
Version: 1.0.2
Summary: Package for generate headers to http requests.
Home-page: https://github.com/TheDevFromKer/Fake-Headers
Author: TheDevFromKer
License: MIT
Platform: UNKNOWN
Classifier: License :: OSI Approved :: MIT License
Classifier: Programming Language :: Python :: 3
Classifier: Programming Language :: Python :: 3.7
Classifier: Operating System :: OS Independent
